omdb/__init__.py
omdb/exceptions.py
omdb/omdb.py
omdb/py.typed
omdb/utilities.py
pyomdbapi-0.2.3.dist-info/LICENSE
pyomdbapi-0.2.3.dist-info/METADATA
pyomdbapi-0.2.3.dist-info/WHEEL
pyomdbapi-0.2.3.dist-info/top_level.txt
pyomdbapi-0.2.3.dist-info/RECORD
