Metadata-Version: 2.1
Name: pyomdbapi
Version: 0.2.3
Summary: OMDB API python wrapper
Author-email: Tyler Barrus <barrust@gmail.com>
License: MIT
Project-URL: Homepage, https://github.com/barrust/pyomdbapi
Project-URL: Bug-tracker, https://github.com/barrust/pyomdbapi/issues
Project-URL: Documentation, https://pyomdbapi.readthedocs.io/
Keywords: python,omdb,omdb-api,API
Classifier: Development Status :: 3 - Alpha
Classifier: Intended Audience :: Developers
Classifier: Intended Audience :: Information Technology
Classifier: Intended Audience :: Science/Research
Classifier: Topic :: Software Development :: Libraries
Classifier: Topic :: Utilities
Classifier: Topic :: Internet
Classifier: License :: OSI Approved
Classifier: License :: OSI Approved :: MIT License
Classifier: Programming Language :: Python :: 3
Classifier: Programming Language :: Python :: 3.5
Classifier: Programming Language :: Python :: 3.6
Classifier: Programming Language :: Python :: 3.7
Classifier: Programming Language :: Python :: 3.8
Classifier: Programming Language :: Python :: 3.9
Classifier: Programming Language :: Python :: 3.10
Classifier: Programming Language :: Python :: 3.11
Requires-Python: >=3.6
License-File: LICENSE
Requires-Dist: requests >=2
